strfseconds.py
strfseconds-0.0.0b1.dist-info/LICENSE
strfseconds-0.0.0b1.dist-info/METADATA
strfseconds-0.0.0b1.dist-info/WHEEL
strfseconds-0.0.0b1.dist-info/top_level.txt
strfseconds-0.0.0b1.dist-info/RECORD
