Metadata-Version: 2.1
Name: strfseconds
Version: 0.0.0b1
Summary: Convert seconds to units of time.
Home-page: https://github.com/remivisser
Author: Remi Visser
Author-email: remivisser@gmail.com
License: MIT
Download-URL: https://github.com/remivisser
Platform: UNKNOWN
Classifier: Intended Audience :: Developers
Classifier: License :: OSI Approved :: MIT License
Classifier: Programming Language :: Python
Classifier: Programming Language :: Python :: 2.7
Classifier: Programming Language :: Python :: 3
Classifier: Operating System :: OS Independent
